main.py
VoiceDunkin-1.0.0.dist-info/METADATA
VoiceDunkin-1.0.0.dist-info/WHEEL
VoiceDunkin-1.0.0.dist-info/entry_points.txt
VoiceDunkin-1.0.0.dist-info/top_level.txt
VoiceDunkin-1.0.0.dist-info/RECORD
